{
  "dataset_id": 8,
  "name": "liver-disorders",
  "Simple": {
    "Dimensionality": 0.017391304347826087,
    "MajorityClassPercentage": NaN,
    "MinorityClassPercentage": NaN,
    "NumberOfClasses": 0.0,
    "NumberOfFeatures": 6.0,
    "NumberOfInstances": 345.0,
    "NumberOfInstancesWithMissingValues": 0.0,
    "PercentageOfBinaryFeatures": 0.0,
    "PercentageOfInstancesWithMissingValues": 0.0,
    "PercentageOfMissingValues": 0.0,
    "PercentageOfNumericFeatures": 100.0,
    "PercentageOfSymbolicFeatures": 0.0
  },
  "Statistical": {
    "MaxKurtosisOfNumericAtts": 13.813911752411268,
    "MaxMeansOfNumericAtts": 90.15942028985508,
    "MaxSkewnessOfNumericAtts": 3.063498642355853,
    "MaxStdDevOfNumericAtts": 39.25461616755085,
    "MeanKurtosisOfNumericAtts": 6.57117573055445,
    "MeanMeansOfNumericAtts": 42.802898550724635,
    "MeanSkewnessOfNumericAtts": 1.6886196204361754,
    "MeanStdDevOfNumericAtts": 15.827503400802176,
    "MinKurtosisOfNumericAtts": 0.7478828309967818,
    "MinMeansOfNumericAtts": 3.4550724637681136,
    "MinSkewnessOfNumericAtts": -0.38843312376254074,
    "MinStdDevOfNumericAtts": 3.337835264577127
  },
  "Information_Theoretic": {
    "ClassEntropy": NaN,
    "EquivalentNumberOfAtts": NaN,
    "MaxAttributeEntropy": NaN,
    "MaxMutualInformation": NaN,
    "MeanAttributeEntropy": NaN,
    "MeanMutualInformation": NaN,
    "MeanNoiseToSignalRatio": NaN,
    "MinAttributeEntropy": NaN,
    "MinMutualInformation": NaN
  },
  "Landmarking": {
    "CfsSubsetEval_DecisionStumpAUC": NaN,
    "CfsSubsetEval_DecisionStumpErrRate": NaN,
    "CfsSubsetEval_NaiveBayesAUC": NaN,
    "CfsSubsetEval_NaiveBayesErrRate": NaN,
    "CfsSubsetEval_kNN1NAUC": NaN,
    "CfsSubsetEval_kNN1NErrRate": NaN,
    "DecisionStumpAUC": NaN,
    "DecisionStumpErrRate": NaN,
    "NaiveBayesAUC": NaN,
    "NaiveBayesErrRate": NaN,
    "REPTreeDepth1AUC": NaN,
    "REPTreeDepth1ErrRate": NaN,
    "RandomTreeDepth1AUC": NaN,
    "RandomTreeDepth1ErrRate": NaN,
    "kNN1NAUC": NaN,
    "kNN1NErrRate": NaN
  },
  "Other": {
    "AutoCorrelation": 0.8255813953488372,
    "CfsSubsetEval_DecisionStumpKappa": NaN,
    "CfsSubsetEval_NaiveBayesKappa": NaN,
    "CfsSubsetEval_kNN1NKappa": NaN,
    "DecisionStumpKappa": NaN,
    "J48.00001.AUC": NaN,
    "J48.00001.ErrRate": NaN,
    "J48.00001.Kappa": NaN,
    "J48.0001.AUC": NaN,
    "J48.0001.ErrRate": NaN,
    "J48.0001.Kappa": NaN,
    "J48.001.AUC": NaN,
    "J48.001.ErrRate": NaN,
    "J48.001.Kappa": NaN,
    "MajorityClassSize": NaN,
    "MaxNominalAttDistinctValues": NaN,
    "MeanNominalAttDistinctValues": NaN,
    "MinNominalAttDistinctValues": NaN,
    "MinorityClassSize": NaN,
    "NaiveBayesKappa": NaN,
    "NumberOfBinaryFeatures": 0.0,
    "NumberOfMissingValues": 0.0,
    "NumberOfNumericFeatures": 6.0,
    "NumberOfSymbolicFeatures": 0.0,
    "Quartile1AttributeEntropy": NaN,
    "Quartile1KurtosisOfNumericAtts": 2.1256888395117097,
    "Quartile1MeansOfNumericAtts": 19.346376811594208,
    "Quartile1MutualInformation": NaN,
    "Quartile1SkewnessOfNumericAtts": 0.4681417978731725,
    "Quartile1StdDevOfNumericAtts": 4.170530797367548,
    "Quartile2AttributeEntropy": NaN,
    "Quartile2KurtosisOfNumericAtts": 5.901776568203553,
    "Quartile2MeansOfNumericAtts": 34.344927536231886,
    "Quartile2MutualInformation": NaN,
    "Quartile2SkewnessOfNumericAtts": 1.918445936350417,
    "Quartile2StdDevOfNumericAtts": 14.206082045720775,
    "Quartile3AttributeEntropy": NaN,
    "Quartile3KurtosisOfNumericAtts": 11.31103980397396,
    "Quartile3MeansOfNumericAtts": 74.94202898550725,
    "Quartile3MutualInformation": NaN,
    "Quartile3SkewnessOfNumericAtts": 2.9154448302673353,
    "Quartile3StdDevOfNumericAtts": 24.44788572159709,
    "REPTreeDepth1Kappa": NaN,
    "REPTreeDepth2AUC": NaN,
    "REPTreeDepth2ErrRate": NaN,
    "REPTreeDepth2Kappa": NaN,
    "REPTreeDepth3AUC": NaN,
    "REPTreeDepth3ErrRate": NaN,
    "REPTreeDepth3Kappa": NaN,
    "RandomTreeDepth1Kappa": NaN,
    "RandomTreeDepth2AUC": NaN,
    "RandomTreeDepth2ErrRate": NaN,
    "RandomTreeDepth2Kappa": NaN,
    "RandomTreeDepth3AUC": NaN,
    "RandomTreeDepth3ErrRate": NaN,
    "RandomTreeDepth3Kappa": NaN,
    "StdvNominalAttDistinctValues": NaN,
    "kNN1NKappa": NaN
  }
}